[
    { "type": "c", "element": "f", "name": "ユエル" },
    { "type": "c", "element": "f", "name": "マギサ" },
    { "type": "c", "element": "f", "name": "アギエルバ" },
    { "type": "c", "element": "f", "name": "ゼタ" },
    { "type": "c", "element": "f", "name": "クラリス" },
    { "type": "c", "element": "f", "name": "パーシヴァル" },
    { "type": "c", "element": "f", "name": "ガンダゴウザ" },
    { "type": "c", "element": "f", "name": "ヘルエス" },

    { "type": "c", "element": "w", "name": "アルタイル" },
    { "type": "c", "element": "w", "name": "リリィ" },
    { "type": "c", "element": "w", "name": "シャルロッテ" },
    { "type": "c", "element": "w", "name": "ランスロット" },
    { "type": "c", "element": "w", "name": "ソシエ" },
    { "type": "c", "element": "w", "name": "シルヴァ" },
    { "type": "c", "element": "w", "name": "ヨダルラーハ (SSR)" },
    { "type": "c", "element": "w", "name": "リルル" },
    
    { "type": "c", "element": "e", "name": "アレーティア" },
    { "type": "c", "element": "e", "name": "カリオストロ" },
    { "type": "c", "element": "e", "name": "アルルメイヤ" },
    { "type": "c", "element": "e", "name": "メルゥ" },
    { "type": "c", "element": "e", "name": "サラ (SSR)" },
    { "type": "c", "element": "e", "name": "ジークフリート" },
    { "type": "c", "element": "e", "name": "ユーステス" },
    
    { "type": "c", "element": "g", "name": "ガウェイン" },
    { "type": "c", "element": "g", "name": "ネツァワルピリ" },
    { "type": "c", "element": "g", "name": "メーテラ" },
    { "type": "c", "element": "g", "name": "レナ" },
    { "type": "c", "element": "g", "name": "カルメリーナ" },
    { "type": "c", "element": "g", "name": "ペトラ (SSR)" },
    { "type": "c", "element": "g", "name": "アンリエット" },
    { "type": "c", "element": "g", "name": "フィーナ (SSR)" },
    
    { "type": "c", "element": "l", "name": "レ・フィーエ" },
    { "type": "c", "element": "l", "name": "サルナーン" },
    { "type": "c", "element": "l", "name": "セルエル" },
    { "type": "c", "element": "l", "name": "ソフィア" },
    { "type": "c", "element": "l", "name": "ジャンヌダルク" },
    { "type": "c", "element": "l", "name": "アルベール" },
    { "type": "c", "element": "l", "name": "アーミラ (SSR)" },

	{ "type": "c", "element": "d", "name": "レディ・グレイ" },
    { "type": "c", "element": "d", "name": "ケルベロス" },
    { "type": "c", "element": "d", "name": "バザラガ" },
    { "type": "c", "element": "d", "name": "ヴィーラ (SSR)" },
    { "type": "c", "element": "d", "name": "サルナーン (闇)" },
    { "type": "c", "element": "d", "name": "ヴァンピィ" },
    { "type": "c", "element": "d", "name": "ナルメア" },
    { "type": "c", "element": "d", "name": "ベアトリクス" },
    
    { "type": "lc", "element": "f", "name": "ラカム(リミテッド)" },
	{ "type": "lc", "element": "w", "name": "カタリナ(リミテッド)" },
    { "type": "lc", "element": "g", "name": "ロゼッタ(リミテッド)" },
    { "type": "lc", "element": "l", "name": "イオ(リミテッド)" },
    
    { "type": "ec", "element": "g", "name": "アンチラ" },
    
    { "type": "w", "element": "f", "name": "グラッドアイ" },		
    { "type": "w", "element": "f", "name": "クリムゾンフィンガー" },
    { "type": "w", "element": "f", "name": "エウリュトスボウ" },
    { "type": "w", "element": "f", "name": "阿修羅" },
    
    { "type": "w", "element": "w", "name": "デュランダル" },
    { "type": "w", "element": "w", "name": "スラーンド" },
    { "type": "w", "element": "w", "name": "虹の弓" },													
    { "type": "w", "element": "w", "name": "鬼丸国綱" },
    													
    { "type": "w", "element": "e", "name": "カルンウェナン" },
    { "type": "w", "element": "e", "name": "パラシュ" },
    { "type": "w", "element": "e", "name": "ガストラフェテス" },
    { "type": "w", "element": "e", "name": "アッキヌフォート" },
	
    { "type": "w", "element": "g", "name": "ジュワユース" },
    { "type": "w", "element": "g", "name": "シェキナーの弓" },
    { "type": "w", "element": "g", "name": "薄緑" },
    
    { "type": "w", "element": "l", "name": "アスクレピオスの杖" },
    { "type": "w", "element": "l", "name": "獅子王戦拳" },
	
    { "type": "w", "element": "d", "name": "ベガルタ" },
    { "type": "w", "element": "d", "name": "グラーシーザー" },
    
    { "type": "s", "element": "f", "name": "アテナ" },
    { "type": "s", "element": "f", "name": "サテュロス" },
    { "type": "s", "element": "f", "name": "フラム＝グラス" },
    { "type": "s", "element": "f", "name": "アグニス" },

    { "type": "s", "element": "w", "name": "マキュラ・マリウス" },
    { "type": "s", "element": "w", "name": "グラニ" },
    { "type": "s", "element": "w", "name": "オケアノス" },
    { "type": "s", "element": "w", "name": "ネプチューン" },
    { "type": "s", "element": "w", "name": "ヴァルナ" },
    { "type": "s", "element": "w", "name": "カグヤ" },

    { "type": "s", "element": "e", "name": "バアル" },
    { "type": "s", "element": "e", "name": "キュベレー" },
    { "type": "s", "element": "e", "name": "メドゥーサ" },
    { "type": "s", "element": "e", "name": "ティターン" },

    { "type": "s", "element": "g", "name": "ケツァルカトル" },
    { "type": "s", "element": "g", "name": "セイレーン" },
    { "type": "s", "element": "g", "name": "ナタク" },
    { "type": "s", "element": "g", "name": "ガルーダ" },
    { "type": "s", "element": "g", "name": "ゼピュロス" },

    { "type": "s", "element": "l", "name": "雷霆公" },
    { "type": "s", "element": "l", "name": "アポロン" },
    { "type": "s", "element": "l", "name": "オーディン" },
    { "type": "s", "element": "l", "name": "ルシフェル" },
    { "type": "s", "element": "l", "name": "ジ・オーダー・グランデ" },
    { "type": "s", "element": "l", "name": "ゼウス" },

    { "type": "s", "element": "d", "name": "サタン" },
    { "type": "s", "element": "d", "name": "バハムート" },
    { "type": "s", "element": "d", "name": "Dエンジェル・オリヴィエ" },
    { "type": "s", "element": "d", "name": "リッチ" },
    { "type": "s", "element": "d", "name": "ハデス" }
]